{"nodes": [{"id": "server_utils_scheduler_ts", "label": "scheduler.ts", "file_type": "code", "source_file": "server/utils/scheduler.ts", "source_location": "L1"}, {"id": "scheduler_calculatenexttime", "label": "calculateNextTime()", "file_type": "code", "source_file": "server/utils/scheduler.ts", "source_location": "L28"}, {"id": "scheduler_createscheduler", "label": "createScheduler()", "file_type": "code", "source_file": "server/utils/scheduler.ts", "source_location": "L47"}], "edges": [{"source": "server_utils_scheduler_ts", "target": "scheduler_calculatenexttime", "relation": "contains", "confidence": "EXTRACTED", "source_file": "server/utils/scheduler.ts", "source_location": "L28", "weight": 1.0}, {"source": "server_utils_scheduler_ts", "target": "scheduler_createscheduler", "relation": "contains", "confidence": "EXTRACTED", "source_file": "server/utils/scheduler.ts", "source_location": "L47", "weight": 1.0}], "raw_calls": [{"caller_nid": "scheduler_calculatenexttime", "callee": "setUTCHours", "source_file": "server/utils/scheduler.ts", "source_location": "L31"}, {"caller_nid": "scheduler_calculatenexttime", "callee": "setUTCDate", "source_file": "server/utils/scheduler.ts", "source_location": "L35"}, {"caller_nid": "scheduler_calculatenexttime", "callee": "getUTCDate", "source_file": "server/utils/scheduler.ts", "source_location": "L35"}]}