{"nodes": [{"id": "client_lib_shortcut_map_ts", "label": "shortcut-map.ts", "file_type": "code", "source_file": "client/lib/shortcut-map.ts", "source_location": "L1"}, {"id": "shortcut_map_getshortcutsfortab", "label": "getShortcutsForTab()", "file_type": "code", "source_file": "client/lib/shortcut-map.ts", "source_location": "L172"}, {"id": "shortcut_map_groupshortcuts", "label": "groupShortcuts()", "file_type": "code", "source_file": "client/lib/shortcut-map.ts", "source_location": "L181"}, {"id": "shortcut_map_getdisplaykey", "label": "getDisplayKey()", "file_type": "code", "source_file": "client/lib/shortcut-map.ts", "source_location": "L199"}, {"id": "shortcut_map_dedupeshortcuts", "label": "dedupeShortcuts()", "file_type": "code", "source_file": "client/lib/shortcut-map.ts", "source_location": "L217"}], "edges": [{"source": "client_lib_shortcut_map_ts", "target": "meta_key", "relation": "imports_from", "confidence": "EXTRACTED", "source_file": "client/lib/shortcut-map.ts", "source_location": "L1", "weight": 1.0}, {"source": "client_lib_shortcut_map_ts", "target": "constants", "relation": "imports_from", "confidence": "EXTRACTED", "source_file": "client/lib/shortcut-map.ts", "source_location": "L2", "weight": 1.0}, {"source": "client_lib_shortcut_map_ts", "target": "shortcut_map_getshortcutsfortab", "relation": "contains", "confidence": "EXTRACTED", "source_file": "client/lib/shortcut-map.ts", "source_location": "L172", "weight": 1.0}, {"source": "client_lib_shortcut_map_ts", "target": "shortcut_map_groupshortcuts", "relation": "contains", "confidence": "EXTRACTED", "source_file": "client/lib/shortcut-map.ts", "source_location": "L181", "weight": 1.0}, {"source": "client_lib_shortcut_map_ts", "target": "shortcut_map_getdisplaykey", "relation": "contains", "confidence": "EXTRACTED", "source_file": "client/lib/shortcut-map.ts", "source_location": "L199", "weight": 1.0}, {"source": "client_lib_shortcut_map_ts", "target": "shortcut_map_dedupeshortcuts", "relation": "contains", "confidence": "EXTRACTED", "source_file": "client/lib/shortcut-map.ts", "source_location": "L217", "weight": 1.0}, {"source": "shortcut_map_dedupeshortcuts", "target": "shortcut_map_getdisplaykey", "relation": "calls", "confidence": "EXTRACTED", "source_file": "client/lib/shortcut-map.ts", "source_location": "L221", "weight": 1.0}], "raw_calls": [{"caller_nid": "shortcut_map_getshortcutsfortab", "callee": "filter", "source_file": "client/lib/shortcut-map.ts", "source_location": "L173"}, {"caller_nid": "shortcut_map_getshortcutsfortab", "callee": "values", "source_file": "client/lib/shortcut-map.ts", "source_location": "L173"}, {"caller_nid": "shortcut_map_groupshortcuts", "callee": "push", "source_file": "client/lib/shortcut-map.ts", "source_location": "L191"}, {"caller_nid": "shortcut_map_getdisplaykey", "callee": "includes", "source_file": "client/lib/shortcut-map.ts", "source_location": "L200"}, {"caller_nid": "shortcut_map_getdisplaykey", "callee": "getMetaShortcutLabel", "source_file": "client/lib/shortcut-map.ts", "source_location": "L201"}, {"caller_nid": "shortcut_map_getdisplaykey", "callee": "replace", "source_file": "client/lib/shortcut-map.ts", "source_location": "L201"}, {"caller_nid": "shortcut_map_dedupeshortcuts", "callee": "get", "source_file": "client/lib/shortcut-map.ts", "source_location": "L222"}, {"caller_nid": "shortcut_map_dedupeshortcuts", "callee": "push", "source_file": "client/lib/shortcut-map.ts", "source_location": "L224"}, {"caller_nid": "shortcut_map_dedupeshortcuts", "callee": "set", "source_file": "client/lib/shortcut-map.ts", "source_location": "L231"}, {"caller_nid": "shortcut_map_dedupeshortcuts", "callee": "push", "source_file": "client/lib/shortcut-map.ts", "source_location": "L232"}]}